pytrate/__init__.py
pytrate/conftest.py
pytrate/foldchange.py
pytrate/helper.py
pytrate/modelbase.py
pytrate/natural_experiments.py
pytrate/pytrate.py
pytrate/seqdf.py
pytrate/tests/__init__.py
pytrate/tests/test_basemodel.py
pytrate/tests/test_foldchange.py
pytrate/tests/test_helper.py
pytrate/tests/test_natural_experiments.py
pytrate/tests/test_pytrate.py
pytrate/tests/test_seqdf.py
pytrate-2.4.3.dist-info/METADATA
pytrate-2.4.3.dist-info/WHEEL
pytrate-2.4.3.dist-info/top_level.txt
pytrate-2.4.3.dist-info/RECORD
