Metadata-Version: 2.4
Name: pytrate
Version: 2.4.3
Summary: Bayesian sequence-titer models.
Author-email: David Pattinson <david.pattinson@wisc.edu>
Requires-Python: <3.12,>3.6
Requires-Dist: adjustText
Requires-Dist: biopython
Requires-Dist: matplotlib
Requires-Dist: numpy
Requires-Dist: pandas
Requires-Dist: pymc
Requires-Dist: scikit-learn
Requires-Dist: scipy
Provides-Extra: dev
Requires-Dist: pytest; extra == "dev"
Requires-Dist: flake8; extra == "dev"
Requires-Dist: pytest-subtests; extra == "dev"
Requires-Dist: pdoc3; extra == "dev"
